tts_watson/TtsWatson.py
tts_watson/__init__.py
tts_watson/__main__.py
tts_watson-1.0.0.dist-info/DESCRIPTION.rst
tts_watson-1.0.0.dist-info/METADATA
tts_watson-1.0.0.dist-info/RECORD
tts_watson-1.0.0.dist-info/WHEEL
tts_watson-1.0.0.dist-info/entry_points.txt
tts_watson-1.0.0.dist-info/metadata.json
tts_watson-1.0.0.dist-info/top_level.txt
