Metadata-Version: 2.0
Name: tts-watson
Version: 1.0.0
Summary: Text to speech using watson
Home-page: https://github.com/HomeHabbit/tts-watson
Author: Arthur Halet
Author-email: arthurh.halet@gmail.com
License: MIT
Keywords: text-to-speech watson
Platform: ALL
Classifier: Topic :: Multimedia :: Sound/Audio :: Speech
Classifier: Topic :: Software Development :: Libraries
Classifier: License :: OSI Approved :: MIT License
Requires-Dist: Flask
Requires-Dist: anyconfig
Requires-Dist: bunch (>=1.0.1)
Requires-Dist: pyaudio (>=0.2.9)
Requires-Dist: pyyaml (>=3.08)
Requires-Dist: requests
